up_nextflap/__init__.py
up_nextflap/libz3.dylib
up_nextflap/nextflap.so
up_nextflap/up_nextflap.py
up_nextflap-0.2.0.dist-info/LICENSE
up_nextflap-0.2.0.dist-info/METADATA
up_nextflap-0.2.0.dist-info/WHEEL
up_nextflap-0.2.0.dist-info/top_level.txt
up_nextflap-0.2.0.dist-info/RECORD
