Metadata-Version: 2.1
Name: up-nextflap
Version: 0.2.0
Summary: up_nextflap
Home-page: https://github.com/aiplan4eu/up-nextflap
Author: Oscar Sapena
Author-email: ossaver@upv.es
License-File: LICENSE
Requires-Dist: numpy
Requires-Dist: unified-planning
